django_pgcli5/__init__.py
django_pgcli5-1.0.1.dist-info/METADATA
django_pgcli5-1.0.1.dist-info/WHEEL
django_pgcli5-1.0.1.dist-info/licenses/AUTHORS.md
django_pgcli5-1.0.1.dist-info/licenses/LICENSE
django_pgcli5-1.0.1.dist-info/RECORD
