Metadata-Version: 2.4
Name: django-pgcli5
Version: 1.0.1
Summary: Database runtime for Django that replaces psql with pgcli.
Project-URL: Homepage, https://github.com/offbyone/django-pgcli5
Author-email: Chris R <offline@offby1.net>, Ash Christopher <ash.christopher@gmail.com>
License: BSD
License-File: AUTHORS.md
License-File: LICENSE
Keywords: django pgcli postgres database
Classifier: Development Status :: 5 - Production/Stable
Classifier: Intended Audience :: Developers
Classifier: License :: OSI Approved :: BSD License
Classifier: Natural Language :: English
Classifier: Programming Language :: Python :: 3.10
Classifier: Programming Language :: Python :: 3.11
Classifier: Programming Language :: Python :: 3.12
Classifier: Programming Language :: Python :: 3.13
Requires-Python: >=3.10
Requires-Dist: django>=5
Requires-Dist: pgcli
Requires-Dist: psycopg
